cPyparsing.cp313-win_amd64.pyd
cpyparsing-2.4.7.2.4.2.dist-info/licenses/LICENSE.txt
cpyparsing-2.4.7.2.4.2.dist-info/METADATA
cpyparsing-2.4.7.2.4.2.dist-info/WHEEL
cpyparsing-2.4.7.2.4.2.dist-info/top_level.txt
cpyparsing-2.4.7.2.4.2.dist-info/RECORD
